simple_paths_algorithm/__init__.py
simple_paths_algorithm/examples/__init__.py
simple_paths_algorithm/examples/examples.py
simple_paths_algorithm/examples/__pycache__/__init__.cpython-36.pyc
simple_paths_algorithm/examples/__pycache__/examples.cpython-36.pyc
simple_paths_algorithm/examples/data/ex_1_edges.csv
simple_paths_algorithm/examples/data/ex_1_nodes.csv
simple_paths_algorithm/examples/data/ex_2_edges.csv
simple_paths_algorithm/examples/data/ex_2_nodes.csv
simple_paths_algorithm/examples/data/ncaa_2009_games.csv
simple_paths_algorithm/examples/data/ncaa_2009_teams.csv
simple_paths_algorithm/examples/data/ncaa_2016_games.csv
simple_paths_algorithm/examples/data/ncaa_2016_teams.csv
simple_paths_algorithm/examples/data/ncaa_2017_games.csv
simple_paths_algorithm/examples/data/ncaa_2017_teams.csv
simple_paths_algorithm/paths_functions/__init__.py
simple_paths_algorithm/paths_functions/paths_functions.py
simple_paths_algorithm/paths_functions/tests/__init__.py
simple_paths_algorithm/paths_functions/tests/test_paths.py
simple_paths_algorithm-0.1.3.dist-info/DESCRIPTION.rst
simple_paths_algorithm-0.1.3.dist-info/METADATA
simple_paths_algorithm-0.1.3.dist-info/RECORD
simple_paths_algorithm-0.1.3.dist-info/WHEEL
simple_paths_algorithm-0.1.3.dist-info/metadata.json
simple_paths_algorithm-0.1.3.dist-info/top_level.txt
