Metadata-Version: 2.0
Name: simple-paths-algorithm
Version: 0.1.3
Summary: 
Home-page: https://github.com/andrew-lee2/simple_paths_algorithm
Author: Andrew Lee, Douglas Shier
Author-email: leeandrew2@gmail.com
License: MIT
Platform: UNKNOWN
Requires-Dist: pandas (==0.22.0)
Requires-Dist: networkx (==2.1)
Requires-Dist: numpy (==1.14.2)
